tally_counter/__init__.py
tally_counter/counter.py
tally_counter/point.py
tally_counter/py.typed
tally_counter/series.py
tally_counter-0.0.14.dist-info/LICENSE
tally_counter-0.0.14.dist-info/METADATA
tally_counter-0.0.14.dist-info/WHEEL
tally_counter-0.0.14.dist-info/top_level.txt
tally_counter-0.0.14.dist-info/RECORD
